<?xml version="1.0" encoding="UTF-8"?> <!-- -*- nxml -*- -->

<dictionary>
  <alphabet>ABCDEFGHIJKLMNOPQRSTUVWXYZÇĞŞƏİÄËÏÖÜabcdefghijklmnopqrstuvwzyzçğşəıäëïöü</alphabet>
  <!-- Symbol definitions -->
  <xi:include xmlns:xi="http://www.w3.org/2001/XInclude" href="apertium-tr-az.symbols.xml"/>

  <pardefs>
    <!-- Nouns -->
    <pardef n="piv/ə__n">
      <e>
        <p>
          <l>ə</l>
          <r>ə<s n="n"/><s n="abs"/><s n="sg"/></r>
        </p>
      </e>
      <e>
        <p>
          <l>əler</l>
          <r>ə<s n="n"/><s n="abs"/><s n="pl"/></r>
        </p>
      </e>
    </pardef>

    <!-- Verbs -->
    <pardef n="iç/mek__vblex">
      <e>
        <p>
          <l>irəm</l>
          <r>mek<s n="vblex"/><s n="pres"/><s n="p1"/><s n="sg"/></r>
        </p>
      </e>
      <e>
        <p>
          <l>irsən</l>
          <r>mek<s n="vblex"/><s n="pres"/><s n="p2"/><s n="sg"/></r>
        </p>
      </e>
      <e>
        <p>
          <l>ir</l>
          <r>mek<s n="vblex"/><s n="pres"/><s n="p3"/><s n="sg"/></r>
        </p>
      </e>
      <e>
        <p>
          <l>irik</l>
          <r>mek<s n="vblex"/><s n="pres"/><s n="p1"/><s n="pl"/></r>
        </p>
      </e>
      <e>
        <p>
          <l>irlər</l>
          <r>mek<s n="vblex"/><s n="pres"/><s n="p2"/><s n="pl"/></r>
        </p>
      </e>
      <e>
        <p>
          <l>ir</l>
          <r>mek<s n="vblex"/><s n="pres"/><s n="p3"/><s n="pl"/></r>
        </p>
      </e>
    </pardef>
  </pardefs>

  <section id="main" type="standard">
    <!-- Nouns -->
    <e lm="pivə"><i>piv</i><par n="piv/ə__n"/></e>

    <!-- Verbs -->
    <e lm="içmek"><i>iç</i><par n="iç/mek__vblex"/></e>
  </section>
</dictionary>
